date_a_scientist/__init__.py
date_a_scientist/agent.py
date_a_scientist/exceptions.py
date_a_scientist-0.1.19.dist-info/LICENSE
date_a_scientist-0.1.19.dist-info/METADATA
date_a_scientist-0.1.19.dist-info/WHEEL
date_a_scientist-0.1.19.dist-info/RECORD
