Metadata-Version: 2.1
Name: date-a-scientist
Version: 0.1.19
Summary: Query dataframes, find issue with your notebook snippets as if a professional data scientist was pair coding with you
License: MIT
Author: IMPRV Dev Team
Author-email: dev@imprv.ai
Requires-Python: >=3.10,<4.0
Classifier: License :: OSI Approved :: MIT License
Classifier: Operating System :: OS Independent
Classifier: Programming Language :: Python :: 3
Classifier: Programming Language :: Python :: 3.10
Classifier: Programming Language :: Python :: 3.11
Classifier: Programming Language :: Python :: 3.12
Requires-Dist: numpy (==1.26.4)
Requires-Dist: pandasai (==2.3.0)
Requires-Dist: pygments (>=2.18.0,<3.0.0)
Requires-Dist: validators (>=0.31.0,<0.32.0)
Project-URL: Homepage, https://github.com/imprv-ai/date-a-scientist
Project-URL: Issues, https://github.com/imprv-ai/date-a-scientist/issues
